zigpy_deconz/__init__.py
zigpy_deconz/api.py
zigpy_deconz/config.py
zigpy_deconz/exception.py
zigpy_deconz/types.py
zigpy_deconz/uart.py
zigpy_deconz/utils.py
zigpy_deconz/zigbee/__init__.py
zigpy_deconz/zigbee/application.py
zigpy_deconz-0.25.3.dist-info/licenses/COPYING
zigpy_deconz-0.25.3.dist-info/licenses/LICENSE
zigpy_deconz-0.25.3.dist-info/METADATA
zigpy_deconz-0.25.3.dist-info/WHEEL
zigpy_deconz-0.25.3.dist-info/top_level.txt
zigpy_deconz-0.25.3.dist-info/RECORD
