Metadata-Version: 2.4
Name: zigpy-deconz
Version: 0.25.3
Summary: A library which communicates with Deconz radios for zigpy
Author-email: Daniel Schmidt <schmidt.d@aon.at>
License: GPL-3.0
Project-URL: repository, https://github.com/zigpy/zigpy-deconz
Requires-Python: >=3.8
License-File: LICENSE
License-File: COPYING
Requires-Dist: voluptuous
Requires-Dist: zigpy>=0.80.0
Requires-Dist: async-timeout; python_version < "3.11"
Provides-Extra: testing
Requires-Dist: pytest>=7.1.2; extra == "testing"
Requires-Dist: pytest-asyncio>=0.19.0; extra == "testing"
Requires-Dist: pytest-timeout>=2.1.0; extra == "testing"
Requires-Dist: pytest-mock>=3.8.2; extra == "testing"
Requires-Dist: pytest-cov>=3.0.0; extra == "testing"
Dynamic: license-file
